apistblz/__init__.py
apistblz/downloadonce.py
apistblz/exceptions.py
apistblz/ratecontrol.py
apistblz/wait_and_retry.py
apistblz-0.1.2.dist-info/LICENSE
apistblz-0.1.2.dist-info/METADATA
apistblz-0.1.2.dist-info/WHEEL
apistblz-0.1.2.dist-info/top_level.txt
apistblz-0.1.2.dist-info/RECORD
