Metadata-Version: 2.1
Name: apistblz
Version: 0.1.2
Summary: Tools to use external web api for download data.
Home-page: https://github.com/nfwprod/apistblz
Author: nfwprod@gmail.com
License: MIT
Platform: UNKNOWN
Classifier: Development Status :: 3 - Alpha
Classifier: Intended Audience :: Developers
Classifier: License :: OSI Approved :: MIT License
Classifier: Operating System :: OS Independent
